galaxycloudrunner/__init__.py
galaxycloudrunner/rules/__init__.py
galaxycloudrunner/rules/cloudlaunch_pulsar.py
galaxycloudrunner/rules/cloudlaunch_pulsar_compat.py
galaxycloudrunner/rules/helper_rules.py
galaxycloudrunner/runners/__init__.py
galaxycloudrunner/runners/cl_pulsar_burst.py
galaxycloudrunner-0.3.0.dist-info/LICENSE
galaxycloudrunner-0.3.0.dist-info/METADATA
galaxycloudrunner-0.3.0.dist-info/WHEEL
galaxycloudrunner-0.3.0.dist-info/top_level.txt
galaxycloudrunner-0.3.0.dist-info/RECORD
