Metadata-Version: 2.1
Name: galaxycloudrunner
Version: 0.3.0
Summary: A library for supporting cloud bursting in Galaxy.
Home-page: https://github.com/cloudve/galaxycloudrunner
Author: Galaxy and GVL projects
Author-email: help@genome.edu.au
License: MIT
Platform: UNKNOWN
Classifier: Development Status :: 3 - Alpha
Classifier: Programming Language :: Python :: 3
Classifier: License :: OSI Approved :: MIT License
Classifier: Intended Audience :: Developers
Classifier: Intended Audience :: System Administrators
Classifier: Operating System :: OS Independent
Classifier: Topic :: Software Development :: Libraries :: Python Modules
Classifier: Programming Language :: Python :: 2.7
Classifier: Programming Language :: Python :: 3
Classifier: Programming Language :: Python :: 3.6
Requires-Dist: cachetools (==3.1.0)
Requires-Dist: cloudlaunch-cli (==0.2.1)
Provides-Extra: dev
Requires-Dist: sphinx ; extra == 'dev'
Requires-Dist: sphinx-rtd-theme ; extra == 'dev'
Requires-Dist: cachetools (==3.1.0) ; extra == 'dev'
Requires-Dist: cloudlaunch-cli (==0.2.1) ; extra == 'dev'
